setup.py
django_lock/__init__.py
django_lock/context_processors.py
django_lock/decorators.py
django_lock/middleware.py
django_lock/views.py
django_lock.egg-info/PKG-INFO
django_lock.egg-info/SOURCES.txt
django_lock.egg-info/dependency_links.txt
django_lock.egg-info/top_level.txt