Metadata-Version: 1.0
Name: django-lock
Version: 1.1
Summary: A protection method for Django views or complete sites.
Home-page: http://code.google.com/p/django-lock/
Author: Chris Beaven
Author-email: smileychris@gmail.com
License: UNKNOWN
Platform: UNKNOWN
